{
    "users": {
        "defaultProfileImage": "/images/default-user-profile.svg",
        "questionMark": "http://intercome.help",
        "chatMark": "#",
        "signUp": "/users/signUp",
        "signIn": "/users/signIn",
        "signOut": "/users/signOut",
        "myPage": "/users/myPage",
        "myAccount": "/users/myAccount",
        "dashboard": "/users/Dashboard",
        "myProject": "/users/myProject",
        "newProject": "/users/newProject",
        "contents": "/users/contents",
        "container": "/users/container",
        "ingredientData": "/users/ingredientData",
        "community": "/users/community",
        "community_add": "/users/community/add",
        "news": "/users/community/news"
    }
}